{
  "parent": "minecraft:recipes/root",
  "criteria": {
    "has_the_recipe": {
      "conditions": {
        "recipe": "deep_aether:yallesite_slab"
      },
      "trigger": "minecraft:recipe_unlocked"
    },
    "has_yallesite": {
      "conditions": {
        "items": [
          {
            "items": [
              "deep_aether:yallesite"
            ]
          }
        ]
      },
      "trigger": "minecraft:inventory_changed"
    }
  },
  "requirements": [
    [
      "has_yallesite",
      "has_the_recipe"
    ]
  ],
  "rewards": {
    "recipes": [
      "deep_aether:yallesite_slab"
    ]
  }
}