{
  "parent": "minecraft:recipes/root",
  "criteria": {
    "has_sun_core": {
      "conditions": {
        "items": [
          {
            "items": [
              "deep_aether:sun_core"
            ]
          }
        ]
      },
      "trigger": "minecraft:inventory_changed"
    },
    "has_the_recipe": {
      "conditions": {
        "recipe": "deep_aether:afterburner"
      },
      "trigger": "minecraft:recipe_unlocked"
    }
  },
  "requirements": [
    [
      "has_sun_core",
      "has_the_recipe"
    ]
  ],
  "rewards": {
    "recipes": [
      "deep_aether:afterburner"
    ]
  },
  "sends_telemetry_event": false
}