{
  "type": "deep_aether:aether_dungeon_loot_no_replacement",
  "chanceToSpawn": 0.8,
  "conditions": [
    {
      "condition": "neoforge:loot_table_id",
      "loot_table_id": "aether:chests/dungeon/silver/silver_dungeon"
    }
  ],
  "items": [
    {
      "data": {
        "Count": 1,
        "id": "deep_aether:skyjade"
      },
      "weight": 90
    },
    {
      "data": {
        "Count": 2,
        "id": "deep_aether:skyjade"
      },
      "weight": 10
    }
  ],
  "totalWeight": 100
}